.coveragerc
.travis.yml
LICENSE
MANIFEST.in
Makefile
Pipfile
Pipfile.lock
README.rst
appveyor.yml
pytest.ini
setup.cfg
setup.py
tox.ini
examples/base_query_and_create_for_neo4j.py
src/graphic/__init__.py
src/graphic/compat.py
src/graphic/gquery.py
src/graphic/graph.py
src/graphic/meta.py
src/graphic/shortcuts.py
src/graphic/utils.py
src/graphic.egg-info/PKG-INFO
src/graphic.egg-info/SOURCES.txt
src/graphic.egg-info/dependency_links.txt
src/graphic.egg-info/not-zip-safe
src/graphic.egg-info/requires.txt
src/graphic.egg-info/top_level.txt
src/graphic/__pycache__/__init__.cpython-34.pyc
src/graphic/__pycache__/__init__.cpython-35.pyc
src/graphic/__pycache__/__init__.cpython-36.pyc
src/graphic/__pycache__/__init__.cpython-37.pyc
src/graphic/__pycache__/__version__.cpython-37.pyc
src/graphic/__pycache__/compat.cpython-34.pyc
src/graphic/__pycache__/compat.cpython-35.pyc
src/graphic/__pycache__/compat.cpython-36.pyc
src/graphic/__pycache__/compat.cpython-37.pyc
src/graphic/__pycache__/gquery.cpython-34.pyc
src/graphic/__pycache__/gquery.cpython-35.pyc
src/graphic/__pycache__/gquery.cpython-36.pyc
src/graphic/__pycache__/gquery.cpython-37.pyc
src/graphic/__pycache__/graph.cpython-34.pyc
src/graphic/__pycache__/graph.cpython-35.pyc
src/graphic/__pycache__/graph.cpython-36.pyc
src/graphic/__pycache__/graph.cpython-37.pyc
src/graphic/__pycache__/meta.cpython-34.pyc
src/graphic/__pycache__/meta.cpython-35.pyc
src/graphic/__pycache__/meta.cpython-36.pyc
src/graphic/__pycache__/meta.cpython-37.pyc
src/graphic/__pycache__/query.cpython-37.pyc
src/graphic/__pycache__/shortcuts.cpython-34.pyc
src/graphic/__pycache__/shortcuts.cpython-35.pyc
src/graphic/__pycache__/shortcuts.cpython-36.pyc
src/graphic/__pycache__/shortcuts.cpython-37.pyc
src/graphic/__pycache__/utils.cpython-34.pyc
src/graphic/__pycache__/utils.cpython-35.pyc
src/graphic/__pycache__/utils.cpython-36.pyc
src/graphic/__pycache__/utils.cpython-37.pyc
src/graphic/engine/__init__.py
src/graphic/engine/__pycache__/__init__.cpython-34.pyc
src/graphic/engine/__pycache__/__init__.cpython-35.pyc
src/graphic/engine/__pycache__/__init__.cpython-36.pyc
src/graphic/engine/__pycache__/__init__.cpython-37.pyc
