Metadata-Version: 2.1
Name: graphic
Version: 1.0.0a6
Summary: More phthonic, humanize way to play with graphdb
Home-page: https://github.com/chuter/graphic
Author: chuter
Author-email: topgun.chuter@gmail.com
License: MIT
Keywords: graph,neo4j,graph algorithms,client
Platform: UNKNOWN
Classifier: Development Status :: 2 - Pre-Alpha
Classifier: Intended Audience :: Developers
Classifier: Natural Language :: Chinese (Simplified)
Classifier: License :: OSI Approved :: MIT License
Classifier: Programming Language :: Python
Classifier: Programming Language :: Python :: 3
Classifier: Programming Language :: Python :: 3.5
Classifier: Programming Language :: Python :: 3.6
Classifier: Programming Language :: Python :: 3.7
Classifier: Programming Language :: Python :: Implementation :: CPython
Classifier: Programming Language :: Python :: Implementation :: PyPy
Requires-Python: >=3.4
Provides-Extra: dev
Provides-Extra: test
